{
  "instruments": [
    {
      "name": "drums",
      "id": 1
    },
    {
      "name": "saxaphone",
      "id": 2
    },
    {
      "name": "guitar",
      "id": 3
    },
    {
      "name": "keyboard",
      "id": 4
    },
    {
      "name": "accordian",
      "id": 5
    },
    {
      "name": "violin",
      "id": 6
    }
  ],
  "pictures": [
    {
      "name": "violin 1",
      "url": "https://images.unsplash.com/photo-1558556405-3071bd8d3ee6?ixlib=rb-1.2.1&ixid=eyJhcHBfaWQiOjEyMDd9&auto=format&fit=crop&w=936&q=80",
      "instrumentId": "6",
      "id": 1
    },
    {
      "name": "violin 2",
      "url": "https://images.unsplash.com/photo-1562040574-b07d4ba71027?ixlib=rb-1.2.1&auto=format&fit=crop&w=1534&q=80",
      "instrumentID": "6",
      "id": 2
    },
    {
      "name": "violin 3",
      "url": "https://images.unsplash.com/photo-1562040574-c335e9fe4894?ixlib=rb-1.2.1&ixid=eyJhcHBfaWQiOjEyMDd9&auto=format&fit=crop&w=1534&q=80",
      "instrumentID": "6",
      "id": 3
    },
    {
      "name": "drums 1",
      "url": "https://images.unsplash.com/photo-1543443374-b6fe10a6ab7b?ixlib=rb-1.2.1&ixid=eyJhcHBfaWQiOjEyMDd9&auto=format&fit=crop&w=1050&q=80",
      "instrumentID": "1",
      "id": 4
    },
    {
      "name": "drums 2",
      "url": "https://images.unsplash.com/photo-1519892300165-cb5542fb47c7?ixlib=rb-1.2.1&ixid=eyJhcHBfaWQiOjEyMDd9&auto=format&fit=crop&w=1050&q=80",
      "instrumentID": "1",
      "id": 5
    },
    {
      "name": "drums 3",
      "url": "https://images.unsplash.com/photo-1544140119-e0ad950faf9e?ixlib=rb-1.2.1&ixid=eyJhcHBfaWQiOjEyMDd9&auto=format&fit=crop&w=1489&q=80",
      "instrumentID": "1",
      "id": 6
    },
    {
      "name": "saxaphone 1",
      "url": "https://images.unsplash.com/photo-1526137794439-629e5479fe9a?ixlib=rb-1.2.1&ixid=eyJhcHBfaWQiOjEyMDd9&auto=format&fit=crop&w=1050&q=80",
      "instrumentID": "2",
      "id": 7
    },
    {
      "name": "saxaphone 2",
      "url": "https://images.unsplash.com/photo-1415201364774-f6f0bb35f28f?ixlib=rb-1.2.1&ixid=eyJhcHBfaWQiOjEyMDd9&auto=format&fit=crop&w=1050&q=80",
      "instrumentID": "2",
      "id": 8
    },
    {
      "name": "saxaphone 3",
      "url": "https://images.unsplash.com/photo-1528143358888-6d3c7f67bd5d?ixlib=rb-1.2.1&ixid=eyJhcHBfaWQiOjEyMDd9&auto=format&fit=crop&w=680&q=80",
      "instrumentID": "2",
      "id": 9
    },
    {
      "name": "guitar 1",
      "url": "https://images.unsplash.com/photo-1543945696-4f1116f30c03?ixlib=rb-1.2.1&ixid=eyJhcHBfaWQiOjEyMDd9&auto=format&fit=crop&w=607&q=80",
      "instrumentID": "3",
      "id": 10
    },
    {
      "name": "guitar 2",
      "url": "https://images.unsplash.com/photo-1516924962500-2b4b3b99ea02?ixlib=rb-1.2.1&ixid=eyJhcHBfaWQiOjEyMDd9&auto=format&fit=crop&w=1050&q=80",
      "instrumentID": "3",
      "id": 11
    },
    {
      "name": "guitar 3",
      "url": "https://images.unsplash.com/photo-1459305272254-33a7d593a851?ixlib=rb-1.2.1&auto=format&fit=crop&w=1050&q=80",
      "instrumentID": "3",
      "id": 12
    },
    {
      "name": "keyboard 1",
      "url": "https://images.unsplash.com/photo-1471614654469-512ee6a4397a?ixlib=rb-1.2.1&ixid=eyJhcHBfaWQiOjEyMDd9&auto=format&fit=crop&w=1050&q=80",
      "instrumentID": "4",
      "id": 13
    },
    {
      "name": "keyboard 2",
      "url": "https://images.unsplash.com/photo-1469939868368-83e00d69432e?ixlib=rb-1.2.1&ixid=eyJhcHBfaWQiOjEyMDd9&auto=format&fit=crop&w=1050&q=80",
      "instrumentID": "4",
      "id": 14
    },
    {
      "name": "keyboard 3",
      "url": "https://images.unsplash.com/photo-1455800507867-8eff5459d8aa?ixlib=rb-1.2.1&ixid=eyJhcHBfaWQiOjEyMDd9&auto=format&fit=crop&w=1050&q=80",
      "instrumentID": "4",
      "id": 15
    },
    {
      "name": "accordian 1",
      "url": "https://images.unsplash.com/photo-1554919564-8d335da7816d?ixlib=rb-1.2.1&ixid=eyJhcHBfaWQiOjEyMDd9&auto=format&fit=crop&w=634&q=80",
      "instrumentID": "5",
      "id": 16
    },
    {
      "name": "accordian 2",
      "url": "https://images.unsplash.com/photo-1504459134801-e65e543112b6?ixlib=rb-1.2.1&ixid=eyJhcHBfaWQiOjEyMDd9&auto=format&fit=crop&w=1050&q=80",
      "instrumentID": "5",
      "id": 17
    },
    {
      "name": "accordian 3",
      "url": "https://images.unsplash.com/photo-1416304646406-414b1009dbe4?ixlib=rb-1.2.1&ixid=eyJhcHBfaWQiOjEyMDd9&auto=format&fit=crop&w=1050&q=80",
      "instrumentID": "5",
      "id": 18
    }
  ]
}
